gammarers/aws_rds_database_running_schedule_stack/__init__.py
gammarers/aws_rds_database_running_schedule_stack/py.typed
gammarers/aws_rds_database_running_schedule_stack/_jsii/__init__.py
gammarers/aws_rds_database_running_schedule_stack/_jsii/aws-rds-database-running-schedule-stack@2.8.2.jsii.tgz
gammarers_aws_rds_database_running_schedule_stack-2.8.2.dist-info/LICENSE
gammarers_aws_rds_database_running_schedule_stack-2.8.2.dist-info/METADATA
gammarers_aws_rds_database_running_schedule_stack-2.8.2.dist-info/WHEEL
gammarers_aws_rds_database_running_schedule_stack-2.8.2.dist-info/top_level.txt
gammarers_aws_rds_database_running_schedule_stack-2.8.2.dist-info/RECORD
